README.rst
outbox.py
setup.py
outbox.egg-info/PKG-INFO
outbox.egg-info/SOURCES.txt
outbox.egg-info/dependency_links.txt
outbox.egg-info/top_level.txt