Metadata-Version: 1.1
Name: outbox
Version: 0.1.2
Summary: SMTP client for Humans.
Home-page: https://bitbucket.org/getoffmalawn/outbox.py
Author: Nathan Hoad
Author-email: nathan@getoffmalawn.com
License: BSD
Platform: UNKNOWN
Classifier: Intended Audience :: Developers
Classifier: Natural Language :: English
Classifier: License :: OSI Approved :: BSD License
Classifier: Programming Language :: Python
Classifier: Programming Language :: Python :: 2.6
Classifier: Programming Language :: Python :: 2.7
Classifier: Programming Language :: Python :: 3.2
